odoo9_addon_account_journal_report-9.0.1.0.0.99.dev3-nspkg.pth
odoo_addons/account_journal_report/README.rst
odoo_addons/account_journal_report/__init__.py
odoo_addons/account_journal_report/__openerp__.py
odoo_addons/account_journal_report/i18n/account_journal_report.pot
odoo_addons/account_journal_report/i18n/ca.po
odoo_addons/account_journal_report/i18n/de.po
odoo_addons/account_journal_report/i18n/es.po
odoo_addons/account_journal_report/i18n/fr.po
odoo_addons/account_journal_report/i18n/pt.po
odoo_addons/account_journal_report/report/__init__.py
odoo_addons/account_journal_report/report/journal_ledger_report.py
odoo_addons/account_journal_report/report/journal_ledger_report_xlsx.py
odoo_addons/account_journal_report/report/reports.xml
odoo_addons/account_journal_report/static/description/icon.png
odoo_addons/account_journal_report/tests/__init__.py
odoo_addons/account_journal_report/tests/test_account_journal_report.py
odoo_addons/account_journal_report/views/templates.xml
odoo_addons/account_journal_report/wizard/__init__.py
odoo_addons/account_journal_report/wizard/wizard_print_journal_ledger.py
odoo_addons/account_journal_report/wizard/wizard_print_journal_ledger_view.xml
odoo9_addon_account_journal_report-9.0.1.0.0.99.dev3.dist-info/METADATA
odoo9_addon_account_journal_report-9.0.1.0.0.99.dev3.dist-info/WHEEL
odoo9_addon_account_journal_report-9.0.1.0.0.99.dev3.dist-info/namespace_packages.txt
odoo9_addon_account_journal_report-9.0.1.0.0.99.dev3.dist-info/top_level.txt
odoo9_addon_account_journal_report-9.0.1.0.0.99.dev3.dist-info/RECORD
